sk_modelcurves/__init__.py
sk_modelcurves/learning_curve.py
sk_modelcurves-0.4.dist-info/DESCRIPTION.rst
sk_modelcurves-0.4.dist-info/METADATA
sk_modelcurves-0.4.dist-info/RECORD
sk_modelcurves-0.4.dist-info/WHEEL
sk_modelcurves-0.4.dist-info/metadata.json
sk_modelcurves-0.4.dist-info/top_level.txt
