Metadata-Version: 2.0
Name: sk-modelcurves
Version: 0.4
Summary: A wrapper for easy plots of learning and validation curves
Home-page: http://github.com/masongallo/sk-modelcurve
Author: Mason Gallo
Author-email: masongallo@gatech.edu
License: MIT
Keywords: sk_modelcurves learning curves validation curves
Platform: UNKNOWN
Classifier: Development Status :: 3 - Alpha
Classifier: License :: OSI Approved :: MIT License
Classifier: Programming Language :: Python :: 2.7
Classifier: Topic :: Scientific/Engineering
Classifier: Topic :: Software Development
